climmands/__init__.py
climmands-0.0.3.dist-info/LICENSE
climmands-0.0.3.dist-info/METADATA
climmands-0.0.3.dist-info/WHEEL
climmands-0.0.3.dist-info/top_level.txt
climmands-0.0.3.dist-info/RECORD
