Metadata-Version: 2.1
Name: climmands
Version: 0.0.3
Summary: A small cli command helper package
Home-page: https://github.com/qwercik/climmands
Author: Eryk Andrzejewski
Author-email: erykandrzejewski@gmail.com
License: UNKNOWN
Platform: UNKNOWN
Classifier: Programming Language :: Python :: 3
Classifier: License :: OSI Approved :: MIT License
Classifier: Operating System :: OS Independent
Requires-Python: >=3.6
